max_min_by_sg/__init__.py
max_min_by_sg/derivatives.txt
max_min_by_sg/finding_stationary_points.py
max_min_by_sg/main.py
max_min_by_sg/points.txt
max_min_by_sg/solving_maxima_minima_for_2_variables.exe
max_min_by_sg-0.4.dist-info/METADATA
max_min_by_sg-0.4.dist-info/WHEEL
max_min_by_sg-0.4.dist-info/entry_points.txt
max_min_by_sg-0.4.dist-info/top_level.txt
max_min_by_sg-0.4.dist-info/RECORD
