Metadata-Version: 2.4
Name: max_min_by_sg
Version: 0.4
Summary: CLI Maxima/Minima Solver using .exe and Python integration
Requires-Python: >=3.6
Dynamic: requires-python
Dynamic: summary
